{
  "swagger": "2.0",
  "info": {
    "title": "Streamify API Documentation",
    "description": "API documentation for the Streamify MERN application",
    "version": "1.0.0"
  },
  "host": "localhost:8000",
  "basePath": "/api/v1",
  "tags": [
    {
      "name": "User",
      "description": "Operations related to user accounts"
    },
    {
      "name": "Videos",
      "description": "Video management and streaming"
    },
    {
      "name": "Likes",
      "description": "Like/Unlike functionality"
    },
    {
      "name": "Comments",
      "description": "Video comment management"
    },
    {
      "name": "Playlists",
      "description": "User collection of videos"
    }
  ],
  "schemes": [
    "http"
  ],
  "securityDefinitions": {
    "bearerAuth": {
      "type": "apiKey",
      "name": "Authorization",
      "in": "header",
      "description": "Enter: Bearer <token>"
    }
  },
  "paths": {
    "/api/v1/healthcheck/": {
      "get": {
        "tags": [
          "System"
        ],
        "summary": "Health Check",
        "description": "",
        "responses": {
          "default": {
            "description": ""
          }
        }
      }
    },
    "/api/v1/users/register": {
      "post": {
        "tags": [
          "User"
        ],
        "description": "",
        "parameters": [
          {
            "name": "body",
            "in": "body",
            "schema": {
              "type": "object",
              "properties": {
                "fullname": {
                  "example": "any"
                },
                "email": {
                  "example": "any"
                },
                "username": {
                  "example": "any"
                },
                "password": {
                  "example": "any"
                }
              }
            }
          }
        ],
        "responses": {
          "201": {
            "description": "Created"
          }
        }
      }
    },
    "/api/v1/users/login": {
      "post": {
        "tags": [
          "User"
        ],
        "description": "",
        "parameters": [
          {
            "name": "body",
            "in": "body",
            "schema": {
              "type": "object",
              "properties": {
                "username": {
                  "example": "any"
                },
                "email": {
                  "example": "any"
                },
                "password": {
                  "example": "any"
                }
              }
            }
          }
        ],
        "responses": {
          "200": {
            "description": "OK"
          }
        }
      }
    },
    "/api/v1/users/refreshToken": {
      "post": {
        "tags": [
          "User"
        ],
        "description": "",
        "responses": {
          "200": {
            "description": "OK"
          }
        }
      }
    },
    "/api/v1/users/logout": {
      "post": {
        "tags": [
          "User"
        ],
        "description": "",
        "responses": {
          "200": {
            "description": "OK"
          }
        },
        "security": [
          {
            "bearerAuth": []
          }
        ]
      }
    },
    "/api/v1/users/changePassword": {
      "post": {
        "tags": [
          "User"
        ],
        "description": "",
        "parameters": [
          {
            "name": "body",
            "in": "body",
            "schema": {
              "type": "object",
              "properties": {
                "oldPassword": {
                  "example": "any"
                },
                "newPassword": {
                  "example": "any"
                }
              }
            }
          }
        ],
        "responses": {
          "200": {
            "description": "OK"
          }
        },
        "security": [
          {
            "bearerAuth": []
          }
        ]
      }
    },
    "/api/v1/users/currentUser": {
      "get": {
        "tags": [
          "User"
        ],
        "description": "",
        "responses": {
          "200": {
            "description": "OK"
          }
        },
        "security": [
          {
            "bearerAuth": []
          }
        ]
      }
    },
    "/api/v1/users/updateDetails": {
      "patch": {
        "tags": [
          "User"
        ],
        "description": "",
        "parameters": [
          {
            "name": "body",
            "in": "body",
            "schema": {
              "type": "object",
              "properties": {
                "fullname": {
                  "example": "any"
                },
                "email": {
                  "example": "any"
                }
              }
            }
          }
        ],
        "responses": {
          "200": {
            "description": "OK"
          }
        },
        "security": [
          {
            "bearerAuth": []
          }
        ]
      }
    },
    "/api/v1/users/updateAvatar": {
      "patch": {
        "tags": [
          "User"
        ],
        "description": "",
        "responses": {
          "200": {
            "description": "OK"
          }
        },
        "security": [
          {
            "bearerAuth": []
          }
        ]
      }
    },
    "/api/v1/users/updateCoverImage": {
      "patch": {
        "tags": [
          "User"
        ],
        "description": "",
        "responses": {
          "200": {
            "description": "OK"
          }
        },
        "security": [
          {
            "bearerAuth": []
          }
        ]
      }
    },
    "/api/v1/users/channel/{username}": {
      "get": {
        "tags": [
          "User"
        ],
        "description": "",
        "parameters": [
          {
            "name": "username",
            "in": "path",
            "required": true,
            "type": "string"
          }
        ],
        "responses": {
          "200": {
            "description": "OK"
          }
        },
        "security": [
          {
            "bearerAuth": []
          }
        ]
      }
    },
    "/api/v1/users/history": {
      "get": {
        "tags": [
          "User"
        ],
        "description": "",
        "responses": {
          "200": {
            "description": "OK"
          }
        },
        "security": [
          {
            "bearerAuth": []
          }
        ]
      }
    },
    "/api/v1/videos/": {
      "get": {
        "tags": [
          "Videos"
        ],
        "description": "",
        "parameters": [
          {
            "name": "page",
            "in": "query",
            "type": "string"
          },
          {
            "name": "limit",
            "in": "query",
            "type": "string"
          },
          {
            "name": "query",
            "in": "query",
            "type": "string"
          },
          {
            "name": "sortBy",
            "in": "query",
            "type": "string"
          },
          {
            "name": "sortType",
            "in": "query",
            "type": "string"
          },
          {
            "name": "userId",
            "in": "query",
            "type": "string"
          }
        ],
        "responses": {
          "200": {
            "description": "OK"
          }
        }
      },
      "post": {
        "tags": [
          "Videos"
        ],
        "description": "",
        "parameters": [
          {
            "name": "body",
            "in": "body",
            "schema": {
              "type": "object",
              "properties": {
                "title": {
                  "example": "any"
                },
                "description": {
                  "example": "any"
                }
              }
            }
          }
        ],
        "responses": {
          "201": {
            "description": "Created"
          }
        },
        "security": [
          {
            "bearerAuth": []
          }
        ]
      }
    },
    "/api/v1/videos/{videoId}": {
      "get": {
        "tags": [
          "Videos"
        ],
        "description": "",
        "parameters": [
          {
            "name": "videoId",
            "in": "path",
            "required": true,
            "type": "string"
          }
        ],
        "responses": {
          "200": {
            "description": "OK"
          }
        },
        "security": [
          {
            "bearerAuth": []
          }
        ]
      },
      "delete": {
        "tags": [
          "Videos"
        ],
        "description": "",
        "parameters": [
          {
            "name": "videoId",
            "in": "path",
            "required": true,
            "type": "string"
          }
        ],
        "responses": {
          "200": {
            "description": "OK"
          }
        },
        "security": [
          {
            "bearerAuth": []
          }
        ]
      },
      "patch": {
        "tags": [
          "Videos"
        ],
        "description": "",
        "parameters": [
          {
            "name": "videoId",
            "in": "path",
            "required": true,
            "type": "string"
          },
          {
            "name": "body",
            "in": "body",
            "schema": {
              "type": "object",
              "properties": {
                "title": {
                  "example": "any"
                },
                "description": {
                  "example": "any"
                }
              }
            }
          }
        ],
        "responses": {
          "200": {
            "description": "OK"
          }
        },
        "security": [
          {
            "bearerAuth": []
          }
        ]
      }
    },
    "/api/v1/videos/toggle/publish/{videoId}": {
      "patch": {
        "tags": [
          "Videos"
        ],
        "description": "",
        "parameters": [
          {
            "name": "videoId",
            "in": "path",
            "required": true,
            "type": "string"
          }
        ],
        "responses": {
          "200": {
            "description": "OK"
          }
        },
        "security": [
          {
            "bearerAuth": []
          }
        ]
      }
    },
    "/api/v1/likes/videos": {
      "get": {
        "tags": [
          "Likes"
        ],
        "description": "",
        "parameters": [
          {
            "name": "page",
            "in": "query",
            "type": "string"
          },
          {
            "name": "limit",
            "in": "query",
            "type": "string"
          },
          {
            "name": "query",
            "in": "query",
            "type": "string"
          }
        ],
        "responses": {
          "200": {
            "description": "OK"
          }
        }
      }
    },
    "/api/v1/likes/videos/liked": {
      "get": {
        "tags": [
          "Likes"
        ],
        "description": "",
        "parameters": [
          {
            "name": "page",
            "in": "query",
            "type": "string"
          },
          {
            "name": "limit",
            "in": "query",
            "type": "string"
          }
        ],
        "responses": {
          "200": {
            "description": "OK"
          }
        },
        "security": [
          {
            "bearerAuth": []
          }
        ]
      }
    },
    "/api/v1/likes/toggle/v/{videoId}": {
      "post": {
        "tags": [
          "Likes"
        ],
        "description": "",
        "parameters": [
          {
            "name": "videoId",
            "in": "path",
            "required": true,
            "type": "string"
          }
        ],
        "responses": {
          "200": {
            "description": "OK"
          }
        },
        "security": [
          {
            "bearerAuth": []
          }
        ]
      }
    },
    "/api/v1/likes/toggle/c/{commentId}": {
      "post": {
        "tags": [
          "Likes"
        ],
        "description": "",
        "parameters": [
          {
            "name": "commentId",
            "in": "path",
            "required": true,
            "type": "string"
          }
        ],
        "responses": {
          "200": {
            "description": "OK"
          }
        },
        "security": [
          {
            "bearerAuth": []
          }
        ]
      }
    },
    "/api/v1/comments/{videoId}": {
      "post": {
        "tags": [
          "Comments"
        ],
        "description": "",
        "parameters": [
          {
            "name": "videoId",
            "in": "path",
            "required": true,
            "type": "string"
          },
          {
            "name": "body",
            "in": "body",
            "schema": {
              "type": "object",
              "properties": {
                "commentContent": {
                  "example": "any"
                }
              }
            }
          }
        ],
        "responses": {
          "200": {
            "description": "OK"
          }
        },
        "security": [
          {
            "bearerAuth": []
          }
        ]
      }
    },
    "/api/v1/comments/c/{commentId}": {
      "delete": {
        "tags": [
          "Comments"
        ],
        "description": "",
        "parameters": [
          {
            "name": "commentId",
            "in": "path",
            "required": true,
            "type": "string"
          }
        ],
        "responses": {
          "200": {
            "description": "OK"
          }
        },
        "security": [
          {
            "bearerAuth": []
          }
        ]
      },
      "patch": {
        "tags": [
          "Comments"
        ],
        "description": "",
        "parameters": [
          {
            "name": "commentId",
            "in": "path",
            "required": true,
            "type": "string"
          },
          {
            "name": "body",
            "in": "body",
            "schema": {
              "type": "object",
              "properties": {
                "newComment": {
                  "example": "any"
                }
              }
            }
          }
        ],
        "responses": {
          "200": {
            "description": "OK"
          }
        },
        "security": [
          {
            "bearerAuth": []
          }
        ]
      }
    },
    "/api/v1/subscription/{userId}": {
      "post": {
        "tags": [
          "Subscriptions"
        ],
        "description": "",
        "parameters": [
          {
            "name": "userId",
            "in": "path",
            "required": true,
            "type": "string"
          }
        ],
        "responses": {
          "201": {
            "description": "Created"
          }
        },
        "security": [
          {
            "bearerAuth": []
          }
        ]
      }
    },
    "/api/v1/subscription/toggle/{channelId}": {
      "post": {
        "tags": [
          "Subscriptions"
        ],
        "description": "",
        "parameters": [
          {
            "name": "channelId",
            "in": "path",
            "required": true,
            "type": "string"
          }
        ],
        "responses": {
          "200": {
            "description": "OK"
          },
          "201": {
            "description": "Created"
          }
        },
        "security": [
          {
            "bearerAuth": []
          }
        ]
      }
    },
    "/api/v1/subscription/subscriber/{channelId}": {
      "get": {
        "tags": [
          "Subscriptions"
        ],
        "description": "",
        "parameters": [
          {
            "name": "channelId",
            "in": "path",
            "required": true,
            "type": "string"
          }
        ],
        "responses": {
          "200": {
            "description": "OK"
          }
        },
        "security": [
          {
            "bearerAuth": []
          }
        ]
      }
    },
    "/api/v1/subscription/subscribedto/{subscriberId}": {
      "get": {
        "tags": [
          "Subscriptions"
        ],
        "description": "",
        "parameters": [
          {
            "name": "subscriberId",
            "in": "path",
            "required": true,
            "type": "string"
          }
        ],
        "responses": {
          "200": {
            "description": "OK"
          }
        },
        "security": [
          {
            "bearerAuth": []
          }
        ]
      }
    },
    "/api/v1/playlist/": {
      "post": {
        "tags": [
          "Playlists"
        ],
        "description": "",
        "parameters": [
          {
            "name": "body",
            "in": "body",
            "schema": {
              "type": "object",
              "properties": {
                "name": {
                  "example": "any"
                },
                "description": {
                  "example": "any"
                }
              }
            }
          }
        ],
        "responses": {
          "201": {
            "description": "Created"
          }
        },
        "security": [
          {
            "bearerAuth": []
          }
        ]
      }
    },
    "/api/v1/playlist/{playlistId}": {
      "get": {
        "tags": [
          "Playlists"
        ],
        "description": "",
        "parameters": [
          {
            "name": "playlistId",
            "in": "path",
            "required": true,
            "type": "string"
          }
        ],
        "responses": {
          "200": {
            "description": "OK"
          }
        },
        "security": [
          {
            "bearerAuth": []
          }
        ]
      },
      "delete": {
        "tags": [
          "Playlists"
        ],
        "description": "",
        "parameters": [
          {
            "name": "playlistId",
            "in": "path",
            "required": true,
            "type": "string"
          }
        ],
        "responses": {
          "default": {
            "description": ""
          }
        },
        "security": [
          {
            "bearerAuth": []
          }
        ]
      },
      "patch": {
        "tags": [
          "Playlists"
        ],
        "description": "",
        "parameters": [
          {
            "name": "playlistId",
            "in": "path",
            "required": true,
            "type": "string"
          }
        ],
        "responses": {
          "default": {
            "description": ""
          }
        },
        "security": [
          {
            "bearerAuth": []
          }
        ]
      }
    },
    "/api/v1/playlist/add/{videoId}/{playlistId}": {
      "patch": {
        "tags": [
          "Playlists"
        ],
        "description": "",
        "parameters": [
          {
            "name": "videoId",
            "in": "path",
            "required": true,
            "type": "string"
          },
          {
            "name": "playlistId",
            "in": "path",
            "required": true,
            "type": "string"
          }
        ],
        "responses": {
          "200": {
            "description": "OK"
          }
        },
        "security": [
          {
            "bearerAuth": []
          }
        ]
      }
    },
    "/api/v1/playlist/remove/{videoId}/{playlistId}": {
      "patch": {
        "tags": [
          "Playlists"
        ],
        "description": "",
        "parameters": [
          {
            "name": "videoId",
            "in": "path",
            "required": true,
            "type": "string"
          },
          {
            "name": "playlistId",
            "in": "path",
            "required": true,
            "type": "string"
          }
        ],
        "responses": {
          "default": {
            "description": ""
          }
        },
        "security": [
          {
            "bearerAuth": []
          }
        ]
      }
    },
    "/api/v1/playlist/user/{userId}": {
      "get": {
        "tags": [
          "Playlists"
        ],
        "description": "",
        "parameters": [
          {
            "name": "userId",
            "in": "path",
            "required": true,
            "type": "string"
          }
        ],
        "responses": {
          "200": {
            "description": "OK"
          }
        },
        "security": [
          {
            "bearerAuth": []
          }
        ]
      }
    },
    "/api/v1/dashboard/stats": {
      "get": {
        "tags": [
          "Dashboard"
        ],
        "description": "",
        "responses": {
          "200": {
            "description": "OK"
          }
        },
        "security": [
          {
            "bearerAuth": []
          }
        ]
      }
    },
    "/api/v1/dashboard/videos": {
      "get": {
        "tags": [
          "Dashboard"
        ],
        "description": "",
        "responses": {
          "200": {
            "description": "OK"
          }
        },
        "security": [
          {
            "bearerAuth": []
          }
        ]
      }
    }
  }
}